mkdocstrings_graphql-0.3.0.dist-info/METADATA
mkdocstrings_graphql-0.3.0.dist-info/WHEEL
mkdocstrings_graphql-0.3.0.dist-info/entry_points.txt
mkdocstrings_graphql-0.3.0.dist-info/licenses/LICENSE
mkdocstrings_handlers/graphql/__init__.py
mkdocstrings_handlers/graphql/_internal/__init__.py
mkdocstrings_handlers/graphql/_internal/collections.py
mkdocstrings_handlers/graphql/_internal/config.py
mkdocstrings_handlers/graphql/_internal/docstring_models.py
mkdocstrings_handlers/graphql/_internal/enumerations.py
mkdocstrings_handlers/graphql/_internal/errors.py
mkdocstrings_handlers/graphql/_internal/expressions.py
mkdocstrings_handlers/graphql/_internal/handler.py
mkdocstrings_handlers/graphql/_internal/loader.py
mkdocstrings_handlers/graphql/_internal/models.py
mkdocstrings_handlers/graphql/_internal/render.py
mkdocstrings_handlers/graphql/py.typed
mkdocstrings_handlers/graphql/templates/material/_base/docstring.html.jinja
mkdocstrings_handlers/graphql/templates/material/_base/docstring/arguments.html.jinja
mkdocstrings_handlers/graphql/templates/material/_base/docstring/enum_values.html.jinja
mkdocstrings_handlers/graphql/templates/material/_base/docstring/fields.html.jinja
mkdocstrings_handlers/graphql/templates/material/_base/docstring/returns.html.jinja
mkdocstrings_handlers/graphql/templates/material/_base/expression.html.jinja
mkdocstrings_handlers/graphql/templates/material/_base/gql_enum.html.jinja
mkdocstrings_handlers/graphql/templates/material/_base/gql_object.html.jinja
mkdocstrings_handlers/graphql/templates/material/_base/gql_operation.html.jinja
mkdocstrings_handlers/graphql/templates/material/_base/gql_scalar.html.jinja
mkdocstrings_handlers/graphql/templates/material/_base/gql_union.html.jinja
mkdocstrings_handlers/graphql/templates/material/_base/signature.html.jinja
mkdocstrings_handlers/graphql/templates/material/docstring.html.jinja
mkdocstrings_handlers/graphql/templates/material/docstring/arguments.html.jinja
mkdocstrings_handlers/graphql/templates/material/docstring/enum_values.html.jinja
mkdocstrings_handlers/graphql/templates/material/docstring/fields.html.jinja
mkdocstrings_graphql-0.3.0.dist-info/RECORD
